dust_dds-0.14.0.dist-info/METADATA
dust_dds-0.14.0.dist-info/WHEEL
dust_dds.libs/libgcc_s-98a1ef30.so.1
dust_dds/__init__.py
dust_dds/__init__.pyi
dust_dds/dust_dds.cpython-313-x86_64-linux-musl.so
dust_dds/py.typed
dust_dds-0.14.0.dist-info/RECORD
