Metadata-Version: 2.4
Name: dust_dds
Version: 0.14.0
Classifier: License :: OSI Approved :: Apache Software License
Classifier: Development Status :: 5 - Production/Stable
Classifier: Operating System :: OS Independent
Classifier: Programming Language :: Rust
Classifier: Programming Language :: Python :: Implementation :: CPython
Classifier: Programming Language :: Python :: Implementation :: PyPy
Summary: Python bindings for Dust DDS
Home-Page: https://s2e-systems.com/products/dust-dds
Author-email: Joao Rebelo <jrebelo@s2e-systems.com>, Stefan Kimmer <skimmer@s2e-systems.com>
Requires-Python: >=3.8
Project-URL: Homepage, https://www.s2e-systems.com/products/dust-dds
Project-URL: Issues, https://github.com/s2e-systems/dust-dds/issues
Project-URL: Documentation, https://s2e-systems.github.io/dust-dds/dust_dds.html
Project-URL: Repository, https://github.com/s2e-systems/dust-dds
